{
  "schema": 1,
  "kind": "slotapp_counter_template",
  "counter": {
    "name": "SハッピージャグラーVⅢ",
    "rate1": 97,
    "rate2": 98.1,
    "rate3": 99.9,
    "rate4": 102.9,
    "rate5": 105.8,
    "rate6": 108.4,
    "gamesPerHour": 800,
    "betPerGame": 3,
    "availableSettings": "1,2,3,4,5,6"
  },
  "items": [
    {
      "name": "BIG",
      "categoryTag": "ボーナス",
      "diffFlag": "small",
      "countKind": "count",
      "reverseMode": false,
      "prob1": 0.003663,
      "prob2": 0.003693,
      "prob3": 0.0038,
      "prob4": 0.003937,
      "prob5": 0.004181,
      "prob6": 0.004425,
      "displayMode": "denominator",
      "sortOrder": 0,
      "isAutoSum": true,
      "autoSumSourceNames": "単独BIG,チェリー+BIG"
    },
    {
      "name": "REG",
      "categoryTag": "ボーナス",
      "diffFlag": "big",
      "countKind": "count",
      "reverseMode": false,
      "prob1": 0.002518,
      "prob2": 0.002762,
      "prob3": 0.003006,
      "prob4": 0.003327,
      "prob5": 0.003662,
      "prob6": 0.003906,
      "displayMode": "denominator",
      "sortOrder": 1,
      "isAutoSum": true,
      "autoSumSourceNames": "単独REG,チェリー+REG"
    },
    {
      "name": "ボーナス合算",
      "categoryTag": "ボーナス",
      "diffFlag": "medium",
      "countKind": "count",
      "reverseMode": false,
      "prob1": 0.00618,
      "prob2": 0.006456,
      "prob3": 0.006803,
      "prob4": 0.007262,
      "prob5": 0.007843,
      "prob6": 0.008333,
      "displayMode": "denominator",
      "sortOrder": 2,
      "isAutoSum": true
    },
    {
      "name": "単独BIG",
      "categoryTag": "単独ボーナス",
      "diffFlag": "small",
      "countKind": "count",
      "reverseMode": false,
      "prob1": 0.002537,
      "prob2": 0.002579,
      "prob3": 0.002694,
      "prob4": 0.002636,
      "prob5": 0.002862,
      "prob6": 0.00309,
      "displayMode": "denominator",
      "sortOrder": 10
    },
    {
      "name": "単独REG",
      "categoryTag": "単独ボーナス",
      "diffFlag": "big",
      "countKind": "count",
      "reverseMode": false,
      "prob1": 0.001573,
      "prob2": 0.00178,
      "prob3": 0.001878,
      "prob4": 0.002111,
      "prob5": 0.002312,
      "prob6": 0.002344,
      "displayMode": "denominator",
      "sortOrder": 11
    },
    {
      "name": "ブドウ",
      "categoryTag": "小役",
      "diffFlag": "small",
      "countKind": "count",
      "reverseMode": false,
      "prob1": 0.164745,
      "prob2": 0.165837,
      "prob3": 0.166667,
      "prob4": 0.170648,
      "prob5": 0.171233,
      "prob6": 0.172414,
      "displayMode": "denominator",
      "sortOrder": 23
    },
    {
      "name": "チェリー+BIG",
      "categoryTag": "チェリー重複ボーナス",
      "diffFlag": "medium",
      "countKind": "count",
      "reverseMode": false,
      "prob1": 0.000671,
      "prob2": 0.000671,
      "prob3": 0.000671,
      "prob4": 0.000824,
      "prob5": 0.000824,
      "prob6": 0.000824,
      "displayMode": "denominator",
      "sortOrder": 20
    },
    {
      "name": "チェリー+REG",
      "categoryTag": "チェリー重複ボーナス",
      "diffFlag": "medium",
      "countKind": "count",
      "reverseMode": false,
      "prob1": 0.000946,
      "prob2": 0.001007,
      "prob3": 0.001129,
      "prob4": 0.001236,
      "prob5": 0.001373,
      "prob6": 0.001556,
      "displayMode": "denominator",
      "sortOrder": 21
    }
  ]
}
